{
  "target_year": 2026,
  "target_month": 5,
  "timestamp": "2026-06-04T16:16:30.411286",
  "total_expected": 2700,
  "success_count": 2647,
  "skip_count": 2565,
  "fail_count": 53,
  "failed_patterns": [
    {
      "pattern": "【売上】b-03 ジェームス_430_オーディオ.csv",
      "reason": "CSVエクスポートは押せましたが、ダウンロード完了が確認できませんでした（タイムアウト）。"
    },
    {
      "pattern": "【売上】c-01 卸売_411_T-Connect対応ナビ.csv",
      "reason": "CSVエクスポートは押せましたが、ダウンロード完了が確認できませんでした（タイムアウト）。"
    },
    {
      "pattern": "【売上】c-02 直売_411_T-Connect対応ナビ.csv",
      "reason": "CSVエクスポートは押せましたが、ダウンロード完了が確認できませんでした（タイムアウト）。"
    },
    {
      "pattern": "【売上】c-02 直売_413_エントリーナビ.csv",
      "reason": "CSVエクスポートは押せましたが、ダウンロード完了が確認できませんでした（タイムアウト）。"
    },
    {
      "pattern": "【売上】d-01 部品商_411_T-Connect対応ナビ.csv",
      "reason": "CSVエクスポートは押せましたが、ダウンロード完了が確認できませんでした（タイムアウト）。"
    },
    {
      "pattern": "【売上】d-05 用品小売り店_411_T-Connect対応ナビ.csv",
      "reason": "予期せぬ例外エラーが発生しました: 選択肢「411_T-Connect対応ナビ」が見つかりません"
    },
    {
      "pattern": "【売上】e-01 修理工場_415_T-Connectナビキット.csv",
      "reason": "予期せぬ例外エラーが発生しました: 選択肢「415_T-Connectナビキット」が見つかりません"
    },
    {
      "pattern": "【売上】e-02 特定修理業者_237_地場GSユアサ.csv",
      "reason": "予期せぬ例外エラーが発生しました: 選択肢「237_地場GSユアサ」が見つかりません"
    },
    {
      "pattern": "【売上】e-02 特定修理業者_413_エントリーナビ.csv",
      "reason": "予期せぬ例外エラーが発生しました: 選択肢「413_エントリーナビ」が見つかりません"
    },
    {
      "pattern": "【売上】e-03 大口ユーザー_412_ベーシックナビ.csv",
      "reason": "CSVエクスポートは押せましたが、ダウンロード完了が確認できませんでした（タイムアウト）。"
    },
    {
      "pattern": "【売上】e-03 大口ユーザー_510_通信事業.csv",
      "reason": "CSVエクスポートは押せましたが、ダウンロード完了が確認できませんでした（タイムアウト）。"
    },
    {
      "pattern": "【粗利】b-02 外販_411_T-Connect対応ナビ.csv",
      "reason": "CSVエクスポートは押せましたが、ダウンロード完了が確認できませんでした（タイムアウト）。"
    },
    {
      "pattern": "【粗利】b-02 外販_413_エントリーナビ.csv",
      "reason": "CSVエクスポートは押せましたが、ダウンロード完了が確認できませんでした（タイムアウト）。"
    },
    {
      "pattern": "【粗利】b-03 ジェームス_417_本部扱いナビ.csv",
      "reason": "CSVエクスポートは押せましたが、ダウンロード完了が確認できませんでした（タイムアウト）。"
    },
    {
      "pattern": "【粗利】b-03 ジェームス_421_後席ディスプレイ.csv",
      "reason": "CSVエクスポートは押せましたが、ダウンロード完了が確認できませんでした（タイムアウト）。"
    },
    {
      "pattern": "【粗利】d-02 その他再販業者_425_純正ドライブレコーダー.csv",
      "reason": "CSVエクスポートは押せましたが、ダウンロード完了が確認できませんでした（タイムアウト）。"
    },
    {
      "pattern": "【粗利】d-02 その他再販業者_430_オーディオ.csv",
      "reason": "CSVエクスポートは押せましたが、ダウンロード完了が確認できませんでした（タイムアウト）。"
    },
    {
      "pattern": "【粗利】d-03 修理業者_411_T-Connect対応ナビ.csv",
      "reason": "CSVエクスポートは押せましたが、ダウンロード完了が確認できませんでした（タイムアウト）。"
    },
    {
      "pattern": "【粗利】d-03 修理業者_413_エントリーナビ.csv",
      "reason": "CSVエクスポートは押せましたが、ダウンロード完了が確認できませんでした（タイムアウト）。"
    },
    {
      "pattern": "【粗利】d-04 GSS_414_ナビキット.csv",
      "reason": "CSVエクスポートは押せましたが、ダウンロード完了が確認できませんでした（タイムアウト）。"
    },
    {
      "pattern": "【粗利】d-04 GSS_416_エントリーナビキット.csv",
      "reason": "CSVエクスポートは押せましたが、ダウンロード完了が確認できませんでした（タイムアウト）。"
    },
    {
      "pattern": "【粗利】d-04 GSS_911_レクサス車TRD.csv",
      "reason": "CSVエクスポートは押せましたが、ダウンロード完了が確認できませんでした（タイムアウト）。"
    },
    {
      "pattern": "【粗利】d-04 GSS_913_レクサス車モデリスタ.csv",
      "reason": "CSVエクスポートは押せましたが、ダウンロード完了が確認できませんでした（タイムアウト）。"
    },
    {
      "pattern": "【粗利】d-05 用品小売り店_414_ナビキット.csv",
      "reason": "CSVエクスポートは押せましたが、ダウンロード完了が確認できませんでした（タイムアウト）。"
    },
    {
      "pattern": "【粗利】d-05 用品小売り店_415_T-Connectナビキット.csv",
      "reason": "CSVエクスポートは押せましたが、ダウンロード完了が確認できませんでした（タイムアウト）。"
    },
    {
      "pattern": "【粗利】d-05 用品小売り店_416_エントリーナビキット.csv",
      "reason": "CSVエクスポートは押せましたが、ダウンロード完了が確認できませんでした（タイムアウト）。"
    },
    {
      "pattern": "【粗利】d-05 用品小売り店_911_レクサス車TRD.csv",
      "reason": "CSVエクスポートは押せましたが、ダウンロード完了が確認できませんでした（タイムアウト）。"
    },
    {
      "pattern": "【粗利】d-05 用品小売り店_913_レクサス車モデリスタ.csv",
      "reason": "CSVエクスポートは押せましたが、ダウンロード完了が確認できませんでした（タイムアウト）。"
    },
    {
      "pattern": "【粗利】d-06 その他_412_ベーシックナビ.csv",
      "reason": "CSVエクスポートは押せましたが、ダウンロード完了が確認できませんでした（タイムアウト）。"
    },
    {
      "pattern": "【粗利】d-06 その他_416_エントリーナビキット.csv",
      "reason": "CSVエクスポートは押せましたが、ダウンロード完了が確認できませんでした（タイムアウト）。"
    },
    {
      "pattern": "【粗利】e-01 修理工場_411_T-Connect対応ナビ.csv",
      "reason": "CSVエクスポートは押せましたが、ダウンロード完了が確認できませんでした（タイムアウト）。"
    },
    {
      "pattern": "【粗利】e-01 修理工場_413_エントリーナビ.csv",
      "reason": "予期せぬ例外エラーが発生しました: 選択肢「413_エントリーナビ」が見つかりません"
    },
    {
      "pattern": "【粗利】e-02 特定修理業者_236_地場パナソニック.csv",
      "reason": "売上/粗利またはルートのフィルター切り替え失敗のため安全にスキップされました。"
    },
    {
      "pattern": "【粗利】e-02 特定修理業者_237_地場GSユアサ.csv",
      "reason": "売上/粗利またはルートのフィルター切り替え失敗のため安全にスキップされました。"
    },
    {
      "pattern": "【粗利】e-02 特定修理業者_245_礦油その他.csv",
      "reason": "売上/粗利またはルートのフィルター切り替え失敗のため安全にスキップされました。"
    },
    {
      "pattern": "【粗利】e-02 特定修理業者_411_T-Connect対応ナビ.csv",
      "reason": "売上/粗利またはルートのフィルター切り替え失敗のため安全にスキップされました。"
    },
    {
      "pattern": "【粗利】e-02 特定修理業者_412_ベーシックナビ.csv",
      "reason": "売上/粗利またはルートのフィルター切り替え失敗のため安全にスキップされました。"
    },
    {
      "pattern": "【粗利】e-02 特定修理業者_413_エントリーナビ.csv",
      "reason": "売上/粗利またはルートのフィルター切り替え失敗のため安全にスキップされました。"
    },
    {
      "pattern": "【粗利】e-02 特定修理業者_415_T-Connectナビキット.csv",
      "reason": "売上/粗利またはルートのフィルター切り替え失敗のため安全にスキップされました。"
    },
    {
      "pattern": "【粗利】e-02 特定修理業者_425_純正ドライブレコーダー.csv",
      "reason": "売上/粗利またはルートのフィルター切り替え失敗のため安全にスキップされました。"
    },
    {
      "pattern": "【粗利】e-02 特定修理業者_461_後付け安全4商品.csv",
      "reason": "売上/粗利またはルートのフィルター切り替え失敗のため安全にスキップされました。"
    },
    {
      "pattern": "【粗利】e-03 大口ユーザー_321_S部品.csv",
      "reason": "売上/粗利またはルートのフィルター切り替え失敗のため安全にスキップされました。"
    },
    {
      "pattern": "【粗利】e-03 大口ユーザー_236_地場パナソニック.csv",
      "reason": "売上/粗利またはルートのフィルター切り替え失敗のため安全にスキップされました。"
    },
    {
      "pattern": "【粗利】e-03 大口ユーザー_411_T-Connect対応ナビ.csv",
      "reason": "売上/粗利またはルートのフィルター切り替え失敗のため安全にスキップされました。"
    },
    {
      "pattern": "【粗利】e-03 大口ユーザー_412_ベーシックナビ.csv",
      "reason": "売上/粗利またはルートのフィルター切り替え失敗のため安全にスキップされました。"
    },
    {
      "pattern": "【粗利】e-03 大口ユーザー_413_エントリーナビ.csv",
      "reason": "売上/粗利またはルートのフィルター切り替え失敗のため安全にスキップされました。"
    },
    {
      "pattern": "【粗利】e-03 大口ユーザー_414_ナビキット.csv",
      "reason": "売上/粗利またはルートのフィルター切り替え失敗のため安全にスキップされました。"
    },
    {
      "pattern": "【粗利】e-03 大口ユーザー_416_エントリーナビキット.csv",
      "reason": "売上/粗利またはルートのフィルター切り替え失敗のため安全にスキップされました。"
    },
    {
      "pattern": "【粗利】e-03 大口ユーザー_417_本部扱いナビ.csv",
      "reason": "売上/粗利またはルートのフィルター切り替え失敗のため安全にスキップされました。"
    },
    {
      "pattern": "【粗利】e-03 大口ユーザー_425_純正ドライブレコーダー.csv",
      "reason": "売上/粗利またはルートのフィルター切り替え失敗のため安全にスキップされました。"
    },
    {
      "pattern": "【粗利】e-03 大口ユーザー_510_通信事業.csv",
      "reason": "売上/粗利またはルートのフィルター切り替え失敗のため安全にスキップされました。"
    },
    {
      "pattern": "【粗利】e-03 大口ユーザー_907_純正ETC2.0.csv",
      "reason": "売上/粗利またはルートのフィルター切り替え失敗のため安全にスキップされました。"
    },
    {
      "pattern": "【粗利】e-03 大口ユーザー_907_純正ETC.csv",
      "reason": "売上/粗利またはルートのフィルター切り替え失敗のため安全にスキップされました。"
    }
  ]
}